Metadata-Version: 2.1
Name: jwt-validator-fdelgados
Version: 2.3.1
Summary: Access tokens validator. Role checker
Home-page: https://github.com/fdelgados/credential-shield.git
Author: Cisco Delgado
Author-email: fdelgados@gmail.com
Requires-Python: >=3.9
License-File: LICENSE.txt
Requires-Dist: PyJWT (==1.5.3)
Requires-Dist: parse (==1.19.0)
Requires-Dist: cryptography (==3.4.7)
